accelerant/__info__.py
accelerant/__init__.py
accelerant/tests/__init__.py
accelerant/tests/__main__.py
accelerant-0.0.1.dev0.dist-info/licenses/LICENSE
accelerant-0.0.1.dev0.dist-info/METADATA
accelerant-0.0.1.dev0.dist-info/WHEEL
accelerant-0.0.1.dev0.dist-info/top_level.txt
accelerant-0.0.1.dev0.dist-info/RECORD
