Metadata-Version: 2.4
Name: accelerant
Version: 0.0.1.dev0
Summary: accelerant for scientific automation
Home-page: https://github.com/Scientific-AI/accelerant
Download-URL: https://pypi.org/project/accelerant/#files
Author: Mike McKerns
Author-email: mmckerns@uqfoundation.org
Maintainer: Mike McKerns
Maintainer-email: mmckerns@uqfoundation.org
License: BSD-3-Clause
Project-URL: Documentation, http://accelerant.rtfd.io
Project-URL: Source Code, https://github.com/Scientific-AI/accelerant
Project-URL: Bug Tracker, https://github.com/Scientific-AI/accelerant/issues
Platform: Linux
Platform: Windows
Platform: Mac
Classifier: Development Status :: 2 - Pre-Alpha
Classifier: Intended Audience :: Developers
Classifier: Intended Audience :: Science/Research
Classifier: License :: OSI Approved :: BSD License
Classifier: Programming Language :: Python :: 3
Classifier: Programming Language :: Python :: 3.9
Classifier: Programming Language :: Python :: 3.10
Classifier: Programming Language :: Python :: 3.11
Classifier: Programming Language :: Python :: 3.12
Classifier: Programming Language :: Python :: 3.13
Classifier: Programming Language :: Python :: Implementation :: CPython
Classifier: Programming Language :: Python :: Implementation :: PyPy
Classifier: Topic :: Scientific/Engineering
Classifier: Topic :: Software Development
Requires-Python: >=3.9
License-File: LICENSE
Dynamic: author
Dynamic: author-email
Dynamic: classifier
Dynamic: description
Dynamic: download-url
Dynamic: home-page
Dynamic: license
Dynamic: license-file
Dynamic: maintainer
Dynamic: maintainer-email
Dynamic: platform
Dynamic: project-url
Dynamic: requires-python
Dynamic: summary
